Metadata-Version: 2.1
Name: ld-estimator
Version: 1.1.2
Summary: Package for estimating linkage disequilibrium
Home-page: https://github.com/jeremymcrae/ld_estimator
Author: Jeremy McRae
Author-email: jmcrae@illumina.com
License: MIT
Platform: UNKNOWN
Classifier: Development Status :: 3 - Alpha
Classifier: Topic :: Scientific/Engineering :: Bio-Informatics
Requires-Python: >3.6.0
